<?xml version="1.0" encoding="utf-8"?>
<QuickFormDefinition Id="09c0fef0-95c8-4e9a-8fcf-708e0f330ef3" name="AccountAccountingInfo">
  <Properties>
    <Property name="EntityTypeName" type="System.String">IAccount</Property>
    <Property name="DefaultNamespace" type="System.String">Sage.Entity.Interfaces</Property>
    <Property name="AssemblyName" type="System.String">Sage.Entity.Interfaces</Property>
    <Property name="UseEntityNameAsTitle" type="System.Boolean">True</Property>
    <Property name="ImagePath" type="System.String"></Property>
    <Property name="DefinitionType" type="System.String">Sage.Platform.QuickForms.QuickFormMainDetailViewDefinition, Sage.Platform.QuickForms</Property>
    <Property name="Columns" type="System.ComponentModel.BindingList`1[[System.Windows.Forms.ColumnStyle, System.Windows.Forms, Version=2.0.0.0, Culture=neutral, PublicKeyToken=b77a5c561934e089]], System, Version=2.0.0.0, Culture=neutral, PublicKeyToken=b77a5c561934e089"><ArrayOfColumnStyle xmlns:xsi="http://www.w3.org/2001/XMLSchema-instance" xmlns:xsd="http://www.w3.org/2001/XMLSchema"><ColumnStyle><SizeType>Percent</SizeType><Width>50</Width></ColumnStyle><ColumnStyle><SizeType>Percent</SizeType><Width>50</Width></ColumnStyle></ArrayOfColumnStyle></Property>
    <Property name="Rows" type="System.ComponentModel.BindingList`1[[System.Windows.Forms.RowStyle, System.Windows.Forms, Version=2.0.0.0, Culture=neutral, PublicKeyToken=b77a5c561934e089]], System, Version=2.0.0.0, Culture=neutral, PublicKeyToken=b77a5c561934e089"><ArrayOfRowStyle xmlns:xsi="http://www.w3.org/2001/XMLSchema-instance" xmlns:xsd="http://www.w3.org/2001/XMLSchema"><RowStyle><SizeType>Absolute</SizeType><Height>35</Height></RowStyle><RowStyle><SizeType>Absolute</SizeType><Height>35</Height></RowStyle><RowStyle><SizeType>Absolute</SizeType><Height>35</Height></RowStyle><RowStyle><SizeType>Absolute</SizeType><Height>35</Height></RowStyle><RowStyle><SizeType>Absolute</SizeType><Height>35</Height></RowStyle><RowStyle><SizeType>Absolute</SizeType><Height>35</Height></RowStyle><RowStyle><SizeType>Absolute</SizeType><Height>35</Height></RowStyle><RowStyle><SizeType>Absolute</SizeType><Height>35</Height></RowStyle><RowStyle><SizeType>Absolute</SizeType><Height>35</Height></RowStyle></ArrayOfRowStyle></Property>
    <Property name="GeneratePrintView" type="System.Boolean">False</Property>
    <Property name="Description" type="System.String"></Property>
    <Property name="ActiveControl" type="System.String"></Property>
  </Properties>
  <LoadActions />
  <QuickFormElements>
    <QuickFormElement>
      <Properties>
        <Property name="EntityMappingType" type="System.String">Property</Property>
        <Property name="EntityTypeName" type="System.String">IAccount</Property>
        <Property name="EntityNamespace" type="System.String">Sage.Entity.Interfaces</Property>
        <Property name="EntityAssemblyName" type="System.String">Sage.Entity.Interfaces</Property>
        <Property name="DefaultNamespace" type="System.String">Sage.Entity.Interfaces</Property>
        <Property name="AssemblyName" type="System.String">Sage.Entity.Interfaces</Property>
        <Property name="EntityReferenceName" type="System.String"></Property>
        <Property name="ValueMember" type="System.String">BankName</Property>
      </Properties>
      <ControlDefinition>
        <Properties>
          <Property name="Control" type="Sage.Platform.QuickForms.Controls.QFTextBox, Sage.Platform.QuickForms"><QFTextBox xmlns:xsi="http://www.w3.org/2001/XMLSchema-instance" xmlns:xsd="http://www.w3.org/2001/XMLSchema"><Column>0</Column><Row>0</Row><IsReadOnly>false</IsReadOnly><HotKey>0</HotKey><TabIndex>0</TabIndex><ControlId>BankName</ControlId><DataBindings><QuickFormPropertyDataBindingDefinition><DataSourceID>MainEntity</DataSourceID><DataItemName>BankName</DataItemName><ControlItemName>Text</ControlItemName><FormatString /><NullValueString /></QuickFormPropertyDataBindingDefinition></DataBindings><ControlLabelPlacement>left</ControlLabelPlacement><CaptionAlignment>left</CaptionAlignment><StyleScheme /><MaxLength>64</MaxLength><OnChangeAction><ResourceKey>BankName</ResourceKey><RootActionName>NoActionAction</RootActionName><Action /><IsDialogCloseAction>False</IsDialogCloseAction><RunOnEveryRePaint>False</RunOnEveryRePaint><DialogActionResult>NoResult</DialogActionResult><PerformsUpdate>False</PerformsUpdate><AppliedSecurity /><RefreshData>False</RefreshData></OnChangeAction></QFTextBox></Property>
        </Properties>
      </ControlDefinition>
    </QuickFormElement>
    <QuickFormElement>
      <Properties>
        <Property name="EntityMappingType" type="System.String">Property</Property>
        <Property name="EntityTypeName" type="System.String">IAccount</Property>
        <Property name="EntityNamespace" type="System.String">Sage.Entity.Interfaces</Property>
        <Property name="EntityAssemblyName" type="System.String">Sage.Entity.Interfaces</Property>
        <Property name="DefaultNamespace" type="System.String">Sage.Entity.Interfaces</Property>
        <Property name="AssemblyName" type="System.String">Sage.Entity.Interfaces</Property>
        <Property name="EntityReferenceName" type="System.String"></Property>
        <Property name="ValueMember" type="System.String">HomeBranchAddress</Property>
      </Properties>
      <ControlDefinition>
        <Properties>
          <Property name="Control" type="Sage.Platform.QuickForms.Controls.QFTextBox, Sage.Platform.QuickForms"><QFTextBox xmlns:xsi="http://www.w3.org/2001/XMLSchema-instance" xmlns:xsd="http://www.w3.org/2001/XMLSchema"><RowSpan>2</RowSpan><Column>0</Column><Row>1</Row><IsReadOnly>false</IsReadOnly><HotKey>0</HotKey><TabIndex>0</TabIndex><ControlId>HomeBranchAddress</ControlId><DataBindings><QuickFormPropertyDataBindingDefinition><DataSourceID>MainEntity</DataSourceID><DataItemName>HomeBranchAddress</DataItemName><ControlItemName>Text</ControlItemName><FormatString /><NullValueString /></QuickFormPropertyDataBindingDefinition></DataBindings><ControlLabelPlacement>left</ControlLabelPlacement><CaptionAlignment>left</CaptionAlignment><StyleScheme /><MaxLength>2147483647</MaxLength><Lines>5</Lines><OnChangeAction><ResourceKey>HomeBranchAddress</ResourceKey><RootActionName>NoActionAction</RootActionName><Action /><IsDialogCloseAction>False</IsDialogCloseAction><RunOnEveryRePaint>False</RunOnEveryRePaint><DialogActionResult>NoResult</DialogActionResult><PerformsUpdate>False</PerformsUpdate><AppliedSecurity /><RefreshData>False</RefreshData></OnChangeAction></QFTextBox></Property>
        </Properties>
      </ControlDefinition>
    </QuickFormElement>
    <QuickFormElement>
      <Properties>
        <Property name="EntityMappingType" type="System.String">Property</Property>
        <Property name="EntityTypeName" type="System.String">IAccount</Property>
        <Property name="EntityNamespace" type="System.String">Sage.Entity.Interfaces</Property>
        <Property name="EntityAssemblyName" type="System.String">Sage.Entity.Interfaces</Property>
        <Property name="DefaultNamespace" type="System.String">Sage.Entity.Interfaces</Property>
        <Property name="AssemblyName" type="System.String">Sage.Entity.Interfaces</Property>
        <Property name="EntityReferenceName" type="System.String"></Property>
        <Property name="ValueMember" type="System.String">PaymentMethod</Property>
      </Properties>
      <ControlDefinition>
        <Properties>
          <Property name="Control" type="Sage.SalesLogix.QuickForms.QFControls.QFSLXPickList, Sage.SalesLogix.QuickForms.QFControls"><QFSLXPickList xmlns:xsi="http://www.w3.org/2001/XMLSchema-instance" xmlns:xsd="http://www.w3.org/2001/XMLSchema"><Column>0</Column><Row>3</Row><IsReadOnly>false</IsReadOnly><HotKey>0</HotKey><TabIndex>0</TabIndex><ControlId>PaymentMethod</ControlId><DataBindings><QuickFormPropertyDataBindingDefinition><DataSourceID>MainEntity</DataSourceID><DataItemName>PaymentMethod</DataItemName><ControlItemName>PickListValue</ControlItemName><FormatString /><NullValueString /></QuickFormPropertyDataBindingDefinition></DataBindings><ControlLabelPlacement>left</ControlLabelPlacement><CaptionAlignment>left</CaptionAlignment><StyleScheme /><MaxLength>255</MaxLength><OnChangeAction><ResourceKey>PaymentMethod</ResourceKey><RootActionName>NoActionAction</RootActionName><Action /><IsDialogCloseAction>False</IsDialogCloseAction><RunOnEveryRePaint>False</RunOnEveryRePaint><DialogActionResult>NoResult</DialogActionResult><PerformsUpdate>False</PerformsUpdate><AppliedSecurity /><RefreshData>False</RefreshData></OnChangeAction><Required>false</Required><AutoPostBack>false</AutoPostBack><PickListName>IntPaymentMethod</PickListName><StorageMode>Text</StorageMode><NameFormatString /><AllowMultiples>false</AllowMultiples><AlphaSort>false</AlphaSort><MustExistInList>true</MustExistInList><NoneEditable>false</NoneEditable><PickListId /><ValueStoredAsText>true</ValueStoredAsText></QFSLXPickList></Property>
        </Properties>
      </ControlDefinition>
    </QuickFormElement>
    <QuickFormElement>
      <Properties>
        <Property name="EntityMappingType" type="System.String">Property</Property>
        <Property name="EntityTypeName" type="System.String">IAccount</Property>
        <Property name="EntityNamespace" type="System.String">Sage.Entity.Interfaces</Property>
        <Property name="EntityAssemblyName" type="System.String">Sage.Entity.Interfaces</Property>
        <Property name="DefaultNamespace" type="System.String">Sage.Entity.Interfaces</Property>
        <Property name="AssemblyName" type="System.String">Sage.Entity.Interfaces</Property>
        <Property name="EntityReferenceName" type="System.String"></Property>
        <Property name="ValueMember" type="System.String">SWIFTNumber</Property>
      </Properties>
      <ControlDefinition>
        <Properties>
          <Property name="Control" type="Sage.Platform.QuickForms.Controls.QFTextBox, Sage.Platform.QuickForms"><QFTextBox xmlns:xsi="http://www.w3.org/2001/XMLSchema-instance" xmlns:xsd="http://www.w3.org/2001/XMLSchema"><Column>0</Column><Row>4</Row><IsReadOnly>false</IsReadOnly><HotKey>0</HotKey><TabIndex>0</TabIndex><ControlId>SWIFTNumber</ControlId><DataBindings><QuickFormPropertyDataBindingDefinition><DataSourceID>MainEntity</DataSourceID><DataItemName>SWIFTNumber</DataItemName><ControlItemName>Text</ControlItemName><FormatString /><NullValueString /></QuickFormPropertyDataBindingDefinition></DataBindings><ControlLabelPlacement>left</ControlLabelPlacement><CaptionAlignment>left</CaptionAlignment><StyleScheme /><MaxLength>64</MaxLength><OnChangeAction><ResourceKey>SWIFTNumber</ResourceKey><RootActionName>NoActionAction</RootActionName><Action /><IsDialogCloseAction>False</IsDialogCloseAction><RunOnEveryRePaint>False</RunOnEveryRePaint><DialogActionResult>NoResult</DialogActionResult><PerformsUpdate>False</PerformsUpdate><AppliedSecurity /><RefreshData>False</RefreshData></OnChangeAction></QFTextBox></Property>
        </Properties>
      </ControlDefinition>
    </QuickFormElement>
    <QuickFormElement>
      <Properties>
        <Property name="EntityMappingType" type="System.String">Property</Property>
        <Property name="EntityTypeName" type="System.String">IAccount</Property>
        <Property name="EntityNamespace" type="System.String">Sage.Entity.Interfaces</Property>
        <Property name="EntityAssemblyName" type="System.String">Sage.Entity.Interfaces</Property>
        <Property name="DefaultNamespace" type="System.String">Sage.Entity.Interfaces</Property>
        <Property name="AssemblyName" type="System.String">Sage.Entity.Interfaces</Property>
        <Property name="EntityReferenceName" type="System.String"></Property>
        <Property name="ValueMember" type="System.String">RoutingNumber</Property>
      </Properties>
      <ControlDefinition>
        <Properties>
          <Property name="Control" type="Sage.Platform.QuickForms.Controls.QFTextBox, Sage.Platform.QuickForms"><QFTextBox xmlns:xsi="http://www.w3.org/2001/XMLSchema-instance" xmlns:xsd="http://www.w3.org/2001/XMLSchema"><Column>0</Column><Row>5</Row><IsReadOnly>false</IsReadOnly><HotKey>0</HotKey><TabIndex>0</TabIndex><ControlId>RoutingNumber</ControlId><DataBindings><QuickFormPropertyDataBindingDefinition><DataSourceID>MainEntity</DataSourceID><DataItemName>RoutingNumber</DataItemName><ControlItemName>Text</ControlItemName><FormatString /><NullValueString /></QuickFormPropertyDataBindingDefinition></DataBindings><ControlLabelPlacement>left</ControlLabelPlacement><CaptionAlignment>left</CaptionAlignment><StyleScheme /><MaxLength>32</MaxLength><OnChangeAction><ResourceKey>RoutingNumber</ResourceKey><RootActionName>NoActionAction</RootActionName><Action /><IsDialogCloseAction>False</IsDialogCloseAction><RunOnEveryRePaint>False</RunOnEveryRePaint><DialogActionResult>NoResult</DialogActionResult><PerformsUpdate>False</PerformsUpdate><AppliedSecurity /><RefreshData>False</RefreshData></OnChangeAction></QFTextBox></Property>
        </Properties>
      </ControlDefinition>
    </QuickFormElement>
    <QuickFormElement>
      <Properties>
        <Property name="EntityMappingType" type="System.String">Property</Property>
        <Property name="EntityTypeName" type="System.String">IAccount</Property>
        <Property name="EntityNamespace" type="System.String">Sage.Entity.Interfaces</Property>
        <Property name="EntityAssemblyName" type="System.String">Sage.Entity.Interfaces</Property>
        <Property name="DefaultNamespace" type="System.String">Sage.Entity.Interfaces</Property>
        <Property name="AssemblyName" type="System.String">Sage.Entity.Interfaces</Property>
        <Property name="EntityReferenceName" type="System.String"></Property>
        <Property name="ValueMember" type="System.String">AccountNumber</Property>
      </Properties>
      <ControlDefinition>
        <Properties>
          <Property name="Control" type="Sage.Platform.QuickForms.Controls.QFTextBox, Sage.Platform.QuickForms"><QFTextBox xmlns:xsi="http://www.w3.org/2001/XMLSchema-instance" xmlns:xsd="http://www.w3.org/2001/XMLSchema"><Column>0</Column><Row>6</Row><IsReadOnly>false</IsReadOnly><HotKey>0</HotKey><TabIndex>0</TabIndex><ControlId>AccountNumber</ControlId><DataBindings><QuickFormPropertyDataBindingDefinition><DataSourceID>MainEntity</DataSourceID><DataItemName>AccountNumber</DataItemName><ControlItemName>Text</ControlItemName><FormatString /><NullValueString /></QuickFormPropertyDataBindingDefinition></DataBindings><ControlLabelPlacement>left</ControlLabelPlacement><CaptionAlignment>left</CaptionAlignment><StyleScheme /><MaxLength>64</MaxLength><OnChangeAction><ResourceKey>AccountNumber</ResourceKey><RootActionName>NoActionAction</RootActionName><Action /><IsDialogCloseAction>False</IsDialogCloseAction><RunOnEveryRePaint>False</RunOnEveryRePaint><DialogActionResult>NoResult</DialogActionResult><PerformsUpdate>False</PerformsUpdate><AppliedSecurity /><RefreshData>False</RefreshData></OnChangeAction></QFTextBox></Property>
        </Properties>
      </ControlDefinition>
    </QuickFormElement>
    <QuickFormElement>
      <Properties>
        <Property name="EntityMappingType" type="System.String">Property</Property>
        <Property name="EntityTypeName" type="System.String">IAccount</Property>
        <Property name="EntityNamespace" type="System.String">Sage.Entity.Interfaces</Property>
        <Property name="EntityAssemblyName" type="System.String">Sage.Entity.Interfaces</Property>
        <Property name="DefaultNamespace" type="System.String">Sage.Entity.Interfaces</Property>
        <Property name="AssemblyName" type="System.String">Sage.Entity.Interfaces</Property>
        <Property name="EntityReferenceName" type="System.String"></Property>
        <Property name="ValueMember" type="System.String">PrimaryBillingContact</Property>
      </Properties>
      <ControlDefinition>
        <Properties>
          <Property name="Control" type="Sage.Platform.QuickForms.Controls.QFTextBox, Sage.Platform.QuickForms"><QFTextBox xmlns:xsi="http://www.w3.org/2001/XMLSchema-instance" xmlns:xsd="http://www.w3.org/2001/XMLSchema"><Column>0</Column><Row>7</Row><IsReadOnly>false</IsReadOnly><HotKey>0</HotKey><TabIndex>0</TabIndex><ControlId>PrimaryBillingContact</ControlId><DataBindings><QuickFormPropertyDataBindingDefinition><DataSourceID>MainEntity</DataSourceID><DataItemName>PrimaryBillingContact</DataItemName><ControlItemName>Text</ControlItemName><FormatString /><NullValueString /></QuickFormPropertyDataBindingDefinition></DataBindings><ControlLabelPlacement>left</ControlLabelPlacement><CaptionAlignment>left</CaptionAlignment><StyleScheme /><MaxLength>128</MaxLength><OnChangeAction><ResourceKey>PrimaryBillingContact</ResourceKey><RootActionName>NoActionAction</RootActionName><Action /><IsDialogCloseAction>False</IsDialogCloseAction><RunOnEveryRePaint>False</RunOnEveryRePaint><DialogActionResult>NoResult</DialogActionResult><PerformsUpdate>False</PerformsUpdate><AppliedSecurity /><RefreshData>False</RefreshData></OnChangeAction></QFTextBox></Property>
        </Properties>
      </ControlDefinition>
    </QuickFormElement>
    <QuickFormElement>
      <Properties>
        <Property name="EntityMappingType" type="System.String">None</Property>
      </Properties>
      <ControlDefinition>
        <Properties>
          <Property name="Control" type="Sage.SalesLogix.QuickForms.QFControls.QFSLXEmail, Sage.SalesLogix.QuickForms.QFControls"><QFSLXEmail xmlns:xsi="http://www.w3.org/2001/XMLSchema-instance" xmlns:xsd="http://www.w3.org/2001/XMLSchema"><Column>0</Column><Row>8</Row><IsReadOnly>false</IsReadOnly><HotKey>0</HotKey><TabIndex>0</TabIndex><ControlId>QFSLXEmail</ControlId><DataBindings><QuickFormPropertyDataBindingDefinition><DataSourceID>MainEntity</DataSourceID><DataItemName>PrimaryBillingContactEmail</DataItemName><ControlItemName>Text</ControlItemName><FormatString /><NullValueString /></QuickFormPropertyDataBindingDefinition></DataBindings><ControlLabelPlacement>left</ControlLabelPlacement><CaptionAlignment>left</CaptionAlignment><StyleScheme /><OnChangeAction><ResourceKey>QFSLXEmail</ResourceKey><RootActionName>NoActionAction</RootActionName><Action /><IsDialogCloseAction>False</IsDialogCloseAction><RunOnEveryRePaint>False</RunOnEveryRePaint><DialogActionResult>NoResult</DialogActionResult><PerformsUpdate>False</PerformsUpdate><AppliedSecurity /><RefreshData>False</RefreshData></OnChangeAction><Required>false</Required></QFSLXEmail></Property>
        </Properties>
      </ControlDefinition>
    </QuickFormElement>
    <QuickFormElement>
      <Properties>
        <Property name="EntityMappingType" type="System.String">Property</Property>
        <Property name="EntityTypeName" type="System.String">IAccount</Property>
        <Property name="EntityNamespace" type="System.String">Sage.Entity.Interfaces</Property>
        <Property name="EntityAssemblyName" type="System.String">Sage.Entity.Interfaces</Property>
        <Property name="DefaultNamespace" type="System.String">Sage.Entity.Interfaces</Property>
        <Property name="AssemblyName" type="System.String">Sage.Entity.Interfaces</Property>
        <Property name="EntityReferenceName" type="System.String"></Property>
        <Property name="ValueMember" type="System.String">ProcessingRate</Property>
      </Properties>
      <ControlDefinition>
        <Properties>
          <Property name="Control" type="Sage.Platform.QuickForms.Controls.QFTextBox, Sage.Platform.QuickForms"><QFTextBox xmlns:xsi="http://www.w3.org/2001/XMLSchema-instance" xmlns:xsd="http://www.w3.org/2001/XMLSchema"><Column>1</Column><Row>0</Row><IsReadOnly>false</IsReadOnly><HotKey>0</HotKey><TabIndex>0</TabIndex><ControlId>ProcessingRate</ControlId><DataBindings><QuickFormPropertyDataBindingDefinition><DataSourceID>MainEntity</DataSourceID><DataItemName>ProcessingRate</DataItemName><ControlItemName>Text</ControlItemName><FormatString /><NullValueString /></QuickFormPropertyDataBindingDefinition></DataBindings><ControlLabelPlacement>left</ControlLabelPlacement><CaptionAlignment>left</CaptionAlignment><StyleScheme /><OnChangeAction><ResourceKey>ProcessingRate</ResourceKey><RootActionName>NoActionAction</RootActionName><Action /><IsDialogCloseAction>False</IsDialogCloseAction><RunOnEveryRePaint>False</RunOnEveryRePaint><DialogActionResult>NoResult</DialogActionResult><PerformsUpdate>False</PerformsUpdate><AppliedSecurity /><RefreshData>False</RefreshData></OnChangeAction></QFTextBox></Property>
        </Properties>
      </ControlDefinition>
    </QuickFormElement>
    <QuickFormElement>
      <Properties>
        <Property name="EntityMappingType" type="System.String">Property</Property>
        <Property name="EntityTypeName" type="System.String">IAccount</Property>
        <Property name="EntityNamespace" type="System.String">Sage.Entity.Interfaces</Property>
        <Property name="EntityAssemblyName" type="System.String">Sage.Entity.Interfaces</Property>
        <Property name="DefaultNamespace" type="System.String">Sage.Entity.Interfaces</Property>
        <Property name="AssemblyName" type="System.String">Sage.Entity.Interfaces</Property>
        <Property name="EntityReferenceName" type="System.String"></Property>
        <Property name="ValueMember" type="System.String">TotalDiscount</Property>
      </Properties>
      <ControlDefinition>
        <Properties>
          <Property name="Control" type="Sage.Platform.QuickForms.Controls.QFTextBox, Sage.Platform.QuickForms"><QFTextBox xmlns:xsi="http://www.w3.org/2001/XMLSchema-instance" xmlns:xsd="http://www.w3.org/2001/XMLSchema"><Column>1</Column><Row>1</Row><IsReadOnly>false</IsReadOnly><HotKey>0</HotKey><TabIndex>0</TabIndex><ControlId>TotalDiscount</ControlId><DataBindings><QuickFormPropertyDataBindingDefinition><DataSourceID>MainEntity</DataSourceID><DataItemName>TotalDiscount</DataItemName><ControlItemName>Text</ControlItemName><FormatString /><NullValueString /></QuickFormPropertyDataBindingDefinition></DataBindings><ControlLabelPlacement>left</ControlLabelPlacement><CaptionAlignment>left</CaptionAlignment><StyleScheme /><OnChangeAction><ResourceKey>TotalDiscount</ResourceKey><RootActionName>NoActionAction</RootActionName><Action /><IsDialogCloseAction>False</IsDialogCloseAction><RunOnEveryRePaint>False</RunOnEveryRePaint><DialogActionResult>NoResult</DialogActionResult><PerformsUpdate>False</PerformsUpdate><AppliedSecurity /><RefreshData>False</RefreshData></OnChangeAction></QFTextBox></Property>
        </Properties>
      </ControlDefinition>
    </QuickFormElement>
    <QuickFormElement>
      <Properties>
        <Property name="EntityMappingType" type="System.String">Property</Property>
        <Property name="EntityTypeName" type="System.String">IAccount</Property>
        <Property name="EntityNamespace" type="System.String">Sage.Entity.Interfaces</Property>
        <Property name="EntityAssemblyName" type="System.String">Sage.Entity.Interfaces</Property>
        <Property name="DefaultNamespace" type="System.String">Sage.Entity.Interfaces</Property>
        <Property name="AssemblyName" type="System.String">Sage.Entity.Interfaces</Property>
        <Property name="EntityReferenceName" type="System.String"></Property>
        <Property name="ValueMember" type="System.String">FXRate</Property>
      </Properties>
      <ControlDefinition>
        <Properties>
          <Property name="Control" type="Sage.Platform.QuickForms.Controls.QFTextBox, Sage.Platform.QuickForms"><QFTextBox xmlns:xsi="http://www.w3.org/2001/XMLSchema-instance" xmlns:xsd="http://www.w3.org/2001/XMLSchema"><Column>1</Column><Row>2</Row><IsReadOnly>false</IsReadOnly><HotKey>0</HotKey><TabIndex>0</TabIndex><ControlId>FXRate</ControlId><DataBindings><QuickFormPropertyDataBindingDefinition><DataSourceID>MainEntity</DataSourceID><DataItemName>FXRate</DataItemName><ControlItemName>Text</ControlItemName><FormatString /><NullValueString /></QuickFormPropertyDataBindingDefinition></DataBindings><ControlLabelPlacement>left</ControlLabelPlacement><CaptionAlignment>left</CaptionAlignment><StyleScheme /><OnChangeAction><ResourceKey>FXRate</ResourceKey><RootActionName>NoActionAction</RootActionName><Action /><IsDialogCloseAction>False</IsDialogCloseAction><RunOnEveryRePaint>False</RunOnEveryRePaint><DialogActionResult>NoResult</DialogActionResult><PerformsUpdate>False</PerformsUpdate><AppliedSecurity /><RefreshData>False</RefreshData></OnChangeAction></QFTextBox></Property>
        </Properties>
      </ControlDefinition>
    </QuickFormElement>
    <QuickFormElement>
      <Properties>
        <Property name="EntityMappingType" type="System.String">Property</Property>
        <Property name="EntityTypeName" type="System.String">IAccount</Property>
        <Property name="EntityNamespace" type="System.String">Sage.Entity.Interfaces</Property>
        <Property name="EntityAssemblyName" type="System.String">Sage.Entity.Interfaces</Property>
        <Property name="DefaultNamespace" type="System.String">Sage.Entity.Interfaces</Property>
        <Property name="AssemblyName" type="System.String">Sage.Entity.Interfaces</Property>
        <Property name="EntityReferenceName" type="System.String"></Property>
        <Property name="ValueMember" type="System.String">PaymentSchedule</Property>
      </Properties>
      <ControlDefinition>
        <Properties>
          <Property name="Control" type="Sage.SalesLogix.QuickForms.QFControls.QFSLXPickList, Sage.SalesLogix.QuickForms.QFControls"><QFSLXPickList xmlns:xsi="http://www.w3.org/2001/XMLSchema-instance" xmlns:xsd="http://www.w3.org/2001/XMLSchema"><Column>1</Column><Row>3</Row><IsReadOnly>false</IsReadOnly><HotKey>0</HotKey><TabIndex>0</TabIndex><ControlId>PaymentSchedule</ControlId><DataBindings><QuickFormPropertyDataBindingDefinition><DataSourceID>MainEntity</DataSourceID><DataItemName>PaymentSchedule</DataItemName><ControlItemName>PickListValue</ControlItemName><FormatString /><NullValueString /></QuickFormPropertyDataBindingDefinition></DataBindings><ControlLabelPlacement>left</ControlLabelPlacement><CaptionAlignment>left</CaptionAlignment><StyleScheme /><MaxLength>255</MaxLength><OnChangeAction><ResourceKey>PaymentSchedule</ResourceKey><RootActionName>NoActionAction</RootActionName><Action /><IsDialogCloseAction>False</IsDialogCloseAction><RunOnEveryRePaint>False</RunOnEveryRePaint><DialogActionResult>NoResult</DialogActionResult><PerformsUpdate>False</PerformsUpdate><AppliedSecurity /><RefreshData>False</RefreshData></OnChangeAction><Required>false</Required><AutoPostBack>false</AutoPostBack><PickListName>intPaymentSchedule</PickListName><StorageMode>Text</StorageMode><NameFormatString /><AllowMultiples>false</AllowMultiples><AlphaSort>false</AlphaSort><MustExistInList>true</MustExistInList><NoneEditable>false</NoneEditable><PickListId /><ValueStoredAsText>true</ValueStoredAsText></QFSLXPickList></Property>
        </Properties>
      </ControlDefinition>
    </QuickFormElement>
    <QuickFormElement>
      <Properties>
        <Property name="EntityMappingType" type="System.String">Property</Property>
        <Property name="EntityTypeName" type="System.String">IAccount</Property>
        <Property name="EntityNamespace" type="System.String">Sage.Entity.Interfaces</Property>
        <Property name="EntityAssemblyName" type="System.String">Sage.Entity.Interfaces</Property>
        <Property name="DefaultNamespace" type="System.String">Sage.Entity.Interfaces</Property>
        <Property name="AssemblyName" type="System.String">Sage.Entity.Interfaces</Property>
        <Property name="EntityReferenceName" type="System.String"></Property>
        <Property name="ValueMember" type="System.String">DomesticShippingCostsCalcs</Property>
      </Properties>
      <ControlDefinition>
        <Properties>
          <Property name="Control" type="Sage.Platform.QuickForms.Controls.QFTextBox, Sage.Platform.QuickForms"><QFTextBox xmlns:xsi="http://www.w3.org/2001/XMLSchema-instance" xmlns:xsd="http://www.w3.org/2001/XMLSchema"><RowSpan>3</RowSpan><Column>1</Column><Row>4</Row><IsReadOnly>false</IsReadOnly><HotKey>0</HotKey><TabIndex>0</TabIndex><ControlId>DomesticShippingCostsCalcs</ControlId><DataBindings><QuickFormPropertyDataBindingDefinition><DataSourceID>MainEntity</DataSourceID><DataItemName>DomesticShippingCostsCalcs</DataItemName><ControlItemName>Text</ControlItemName><FormatString /><NullValueString /></QuickFormPropertyDataBindingDefinition></DataBindings><ControlLabelPlacement>left</ControlLabelPlacement><CaptionAlignment>left</CaptionAlignment><StyleScheme /><MaxLength>255</MaxLength><Lines>3</Lines><OnChangeAction><ResourceKey>DomesticShippingCostsCalcs</ResourceKey><RootActionName>NoActionAction</RootActionName><Action /><IsDialogCloseAction>False</IsDialogCloseAction><RunOnEveryRePaint>False</RunOnEveryRePaint><DialogActionResult>NoResult</DialogActionResult><PerformsUpdate>False</PerformsUpdate><AppliedSecurity /><RefreshData>False</RefreshData></OnChangeAction></QFTextBox></Property>
        </Properties>
      </ControlDefinition>
    </QuickFormElement>
  </QuickFormElements>
  <QuickFormToolElements>
    <QuickFormElement>
      <Properties>
        <Property name="EntityMappingType" type="System.String">None</Property>
      </Properties>
      <ControlDefinition>
        <Properties>
          <Property name="Control" type="Sage.Platform.QuickForms.Controls.QFElementSpacer, Sage.Platform.QuickForms"><QFElementSpacer xmlns:xsi="http://www.w3.org/2001/XMLSchema-instance" xmlns:xsd="http://www.w3.org/2001/XMLSchema"><Column>0</Column><Row>0</Row><IsReadOnly>false</IsReadOnly><HotKey>0</HotKey><TabIndex>0</TabIndex><ControlId /><DataBindings /><ControlLabelPlacement>left</ControlLabelPlacement><CaptionAlignment>left</CaptionAlignment><StyleScheme /></QFElementSpacer></Property>
        </Properties>
      </ControlDefinition>
    </QuickFormElement>
    <QuickFormElement>
      <Properties>
        <Property name="EntityMappingType" type="System.String">None</Property>
      </Properties>
      <ControlDefinition>
        <Properties>
          <Property name="Control" type="Sage.Platform.QuickForms.Controls.QFElementSpacer, Sage.Platform.QuickForms"><QFElementSpacer xmlns:xsi="http://www.w3.org/2001/XMLSchema-instance" xmlns:xsd="http://www.w3.org/2001/XMLSchema"><Column>0</Column><Row>0</Row><IsReadOnly>false</IsReadOnly><HotKey>0</HotKey><TabIndex>0</TabIndex><ControlId /><DataBindings /><ControlLabelPlacement>left</ControlLabelPlacement><CaptionAlignment>left</CaptionAlignment><StyleScheme /></QFElementSpacer></Property>
        </Properties>
      </ControlDefinition>
    </QuickFormElement>
    <QuickFormElement>
      <Properties>
        <Property name="EntityMappingType" type="System.String">None</Property>
      </Properties>
      <ControlDefinition>
        <Properties>
          <Property name="Control" type="Sage.Platform.QuickForms.Controls.QFButton, Sage.Platform.QuickForms"><QFButton xmlns:xsi="http://www.w3.org/2001/XMLSchema-instance" xmlns:xsd="http://www.w3.org/2001/XMLSchema"><Column>0</Column><Row>0</Row><IsReadOnly>false</IsReadOnly><HotKey>0</HotKey><TabIndex>0</TabIndex><ControlId>QFButton</ControlId><DataBindings /><ControlLabelPlacement>none</ControlLabelPlacement><CaptionAlignment>left</CaptionAlignment><StyleScheme /><ButtonType>Icon</ButtonType><Image>[Localization!Global_Images:Save_16x16]</Image><OnClientClick /><OnClickAction><ResourceKey>QFButton</ResourceKey><RootActionName>BusinessRuleAction</RootActionName><Action><BusinessRule>Save</BusinessRule><Object>Account</Object><Parameters /><PassResultsToNextAction>False</PassResultsToNextAction><OnCompleteActionName>NoActionAction</OnCompleteActionName><OnComplete /></Action><IsDialogCloseAction>False</IsDialogCloseAction><RunOnEveryRePaint>False</RunOnEveryRePaint><DialogActionResult>NoResult</DialogActionResult><PerformsUpdate>True</PerformsUpdate><AppliedSecurity /><RefreshData>False</RefreshData></OnClickAction></QFButton></Property>
        </Properties>
      </ControlDefinition>
    </QuickFormElement>
  </QuickFormToolElements>
</QuickFormDefinition>