<?xml version="1.0" encoding="utf-8"?>
<QuickFormDefinition Id="ea8e83ad-e4ee-43b7-93de-e26e4839e27e" name="LeadWebsites">
  <Properties>
    <Property name="EntityTypeName" type="System.String">ILead</Property>
    <Property name="DefaultNamespace" type="System.String">Sage.Entity.Interfaces</Property>
    <Property name="AssemblyName" type="System.String">Sage.Entity.Interfaces</Property>
    <Property name="UseEntityNameAsTitle" type="System.Boolean">True</Property>
    <Property name="ImagePath" type="System.String"></Property>
    <Property name="DefinitionType" type="System.String">Sage.Platform.QuickForms.QuickFormMainDetailViewDefinition, Sage.Platform.QuickForms</Property>
    <Property name="Columns" type="System.ComponentModel.BindingList`1[[System.Windows.Forms.ColumnStyle, System.Windows.Forms, Version=2.0.0.0, Culture=neutral, PublicKeyToken=b77a5c561934e089]], System, Version=2.0.0.0, Culture=neutral, PublicKeyToken=b77a5c561934e089"><ArrayOfColumnStyle xmlns:xsi="http://www.w3.org/2001/XMLSchema-instance" xmlns:xsd="http://www.w3.org/2001/XMLSchema"><ColumnStyle><SizeType>Percent</SizeType><Width>100</Width></ColumnStyle></ArrayOfColumnStyle></Property>
    <Property name="Rows" type="System.ComponentModel.BindingList`1[[System.Windows.Forms.RowStyle, System.Windows.Forms, Version=2.0.0.0, Culture=neutral, PublicKeyToken=b77a5c561934e089]], System, Version=2.0.0.0, Culture=neutral, PublicKeyToken=b77a5c561934e089"><ArrayOfRowStyle xmlns:xsi="http://www.w3.org/2001/XMLSchema-instance" xmlns:xsd="http://www.w3.org/2001/XMLSchema"><RowStyle><SizeType>Absolute</SizeType><Height>35</Height></RowStyle><RowStyle><SizeType>Absolute</SizeType><Height>35</Height></RowStyle></ArrayOfRowStyle></Property>
    <Property name="GeneratePrintView" type="System.Boolean">False</Property>
    <Property name="Description" type="System.String"></Property>
    <Property name="ActiveControl" type="System.String"></Property>
  </Properties>
  <LoadActions />
  <QuickFormElements>
    <QuickFormElement>
      <Properties>
        <Property name="EntityMappingType" type="System.String">None</Property>
      </Properties>
      <ControlDefinition>
        <Properties>
          <Property name="Control" type="Sage.SalesLogix.QuickForms.QFControls.QFDataGrid, Sage.SalesLogix.QuickForms.QFControls"><QFDataGrid xmlns:xsi="http://www.w3.org/2001/XMLSchema-instance" xmlns:xsd="http://www.w3.org/2001/XMLSchema"><Column>0</Column><Row>0</Row><IsReadOnly>false</IsReadOnly><HotKey>0</HotKey><TabIndex>0</TabIndex><ControlId>grdLeadWebsites</ControlId><DataBindings /><ControlLabelPlacement>none</ControlLabelPlacement><CaptionAlignment>left</CaptionAlignment><StyleScheme /><DataSource>dsLeadWebsites</DataSource><EnablePaging>false</EnablePaging><EnableSorting>false</EnableSorting><Columns><QFCustomFormatCol><StyleScheme /><DataField>WebAddress</DataField><ColumnId>0ef1457f-2696-45f9-bb3a-f2c6a401ed15</ColumnId><HorizontalAlignment>left</HorizontalAlignment><HeaderAlignment>left</HeaderAlignment><IsSortable>false</IsSortable><MultiCurrencyDependent>false</MultiCurrencyDependent><FormattingMethodName>WebLink</FormattingMethodName><FormattingCode>protected string WebLink(object name)
{
	return string.Format("&lt;a href=\"http://{0}\"	target=_blank&gt;{0}&lt;/a&gt;", name);
}</FormattingCode></QFCustomFormatCol><QFDataGridCol><StyleScheme /><DataField>Notes</DataField><ColumnId>354e17db-24e2-4d47-a508-24415344465e</ColumnId><HorizontalAlignment>left</HorizontalAlignment><HeaderAlignment>left</HeaderAlignment><IsSortable>false</IsSortable><SortField>Notes</SortField><MultiCurrencyDependent>false</MultiCurrencyDependent></QFDataGridCol><QFEditCol><StyleScheme /><DataField /><ColumnId>e573232d-8bf4-48bc-8865-04152a861ad1</ColumnId><HorizontalAlignment>left</HorizontalAlignment><HeaderAlignment>left</HeaderAlignment><IsSortable>false</IsSortable><MultiCurrencyDependent>false</MultiCurrencyDependent><DialogSpecs><SmartPart>AddEditLeadWebsite</SmartPart><Height>400</Height><Width>600</Width><Top>0</Top><Left>0</Left><EntityType>LeadWebsite</EntityType><ResourceKey>a4ee85db-265a-4a6c-811f-b7c0dfc11393</ResourceKey><CenterDialog>True</CenterDialog></DialogSpecs><AppliedSecurity /></QFEditCol><QFDeleteCol><StyleScheme /><DataField /><ColumnId>3d2cbf5e-6e3b-4c9d-a100-9a7c5dc0e90f</ColumnId><HorizontalAlignment>left</HorizontalAlignment><HeaderAlignment>left</HeaderAlignment><IsSortable>false</IsSortable><MultiCurrencyDependent>false</MultiCurrencyDependent><BusinessRule>Delete</BusinessRule><BusinessRuleObjectName>LeadWebsite</BusinessRuleObjectName><BusinessRuleParameters /><AppliedSecurity /></QFDeleteCol></Columns><RenderVertical>false</RenderVertical><OnRowSelectedAction><ResourceKey>grdLeadWebsites</ResourceKey><RootActionName>NoActionAction</RootActionName><Action /><IsDialogCloseAction>False</IsDialogCloseAction><RunOnEveryRePaint>False</RunOnEveryRePaint><DialogActionResult>NoResult</DialogActionResult><PerformsUpdate>False</PerformsUpdate><AppliedSecurity /><RefreshData>False</RefreshData></OnRowSelectedAction></QFDataGrid></Property>
        </Properties>
      </ControlDefinition>
    </QuickFormElement>
    <QuickFormElement>
      <Properties>
        <Property name="EntityMappingType" type="System.String">None</Property>
      </Properties>
      <ControlDefinition>
        <Properties>
          <Property name="Control" type="Sage.Platform.QuickForms.QFControls.QFDataSource, Sage.Platform.QuickForms.QFControls"><QFDataSource xmlns:xsi="http://www.w3.org/2001/XMLSchema-instance" xmlns:xsd="http://www.w3.org/2001/XMLSchema"><Column>0</Column><Row>1</Row><IsReadOnly>false</IsReadOnly><Visible>false</Visible><HotKey>48</HotKey><TabIndex>0</TabIndex><ControlId>dsLeadWebsites</ControlId><DataBindings /><ControlLabelPlacement>none</ControlLabelPlacement><CaptionAlignment>left</CaptionAlignment><StyleScheme /><EntityTypeName>LeadWebsite</EntityTypeName><GetByMethod /><GetByProperty>LeadWebsites</GetByProperty><UseSmartSelection>true</UseSmartSelection><DataOptional>false</DataOptional></QFDataSource></Property>
        </Properties>
      </ControlDefinition>
    </QuickFormElement>
  </QuickFormElements>
  <QuickFormToolElements>
    <QuickFormElement>
      <Properties>
        <Property name="EntityMappingType" type="System.String">None</Property>
      </Properties>
      <ControlDefinition>
        <Properties>
          <Property name="Control" type="Sage.Platform.QuickForms.Controls.QFElementSpacer, Sage.Platform.QuickForms"><QFElementSpacer xmlns:xsi="http://www.w3.org/2001/XMLSchema-instance" xmlns:xsd="http://www.w3.org/2001/XMLSchema"><Column>0</Column><Row>0</Row><IsReadOnly>false</IsReadOnly><HotKey>0</HotKey><TabIndex>0</TabIndex><ControlId /><DataBindings /><ControlLabelPlacement>left</ControlLabelPlacement><CaptionAlignment>left</CaptionAlignment><StyleScheme /></QFElementSpacer></Property>
        </Properties>
      </ControlDefinition>
    </QuickFormElement>
    <QuickFormElement>
      <Properties>
        <Property name="EntityMappingType" type="System.String">None</Property>
      </Properties>
      <ControlDefinition>
        <Properties>
          <Property name="Control" type="Sage.Platform.QuickForms.Controls.QFElementSpacer, Sage.Platform.QuickForms"><QFElementSpacer xmlns:xsi="http://www.w3.org/2001/XMLSchema-instance" xmlns:xsd="http://www.w3.org/2001/XMLSchema"><Column>0</Column><Row>0</Row><IsReadOnly>false</IsReadOnly><HotKey>0</HotKey><TabIndex>0</TabIndex><ControlId /><DataBindings /><ControlLabelPlacement>left</ControlLabelPlacement><CaptionAlignment>left</CaptionAlignment><StyleScheme /></QFElementSpacer></Property>
        </Properties>
      </ControlDefinition>
    </QuickFormElement>
    <QuickFormElement>
      <Properties>
        <Property name="EntityMappingType" type="System.String">None</Property>
      </Properties>
      <ControlDefinition>
        <Properties>
          <Property name="Control" type="Sage.Platform.QuickForms.Controls.QFButton, Sage.Platform.QuickForms"><QFButton xmlns:xsi="http://www.w3.org/2001/XMLSchema-instance" xmlns:xsd="http://www.w3.org/2001/XMLSchema"><Column>0</Column><Row>0</Row><IsReadOnly>false</IsReadOnly><HotKey>0</HotKey><TabIndex>0</TabIndex><ControlId>QFButton</ControlId><DataBindings /><ControlLabelPlacement>none</ControlLabelPlacement><CaptionAlignment>left</CaptionAlignment><StyleScheme /><ButtonType>Icon</ButtonType><Image>[Localization!Global_Images:plus_16x16]</Image><OnClientClick /><OnClickAction><ResourceKey>QFButton</ResourceKey><RootActionName>InsertChildDialogAction</RootActionName><Action><SmartPart>AddEditLeadWebsite</SmartPart><Height>400</Height><Width>600</Width><Top>0</Top><Left>0</Left><ResourceKey>14b7455d-a073-4db7-af36-1854092ea56c</ResourceKey><ParentRelationshipPropertyName>Lead</ParentRelationshipPropertyName><DataSource>dsLeadWebsites</DataSource><CenterDialog>True</CenterDialog></Action><IsDialogCloseAction>False</IsDialogCloseAction><RunOnEveryRePaint>False</RunOnEveryRePaint><DialogActionResult>NoResult</DialogActionResult><PerformsUpdate>True</PerformsUpdate><AppliedSecurity /><RefreshData>False</RefreshData></OnClickAction></QFButton></Property>
        </Properties>
      </ControlDefinition>
    </QuickFormElement>
  </QuickFormToolElements>
</QuickFormDefinition>